py_kaos_utils/__init__.py
py_kaos_utils/argparse.py
py_kaos_utils/logging.py
py_kaos_utils/mixins.py
py_kaos_utils/pagination.py
py_kaos_utils/string.py
py_kaos_utils/typing.py
py_kaos_utils-0.1.0rc1.data/scripts/ppm
tests/__init__.py
tests/test_argparse.py
tests/test_logging.py
tests/test_mixins.py
tests/test_pagination.py
tests/test_string.py
py_kaos_utils-0.1.0rc1.dist-info/LICENSE
py_kaos_utils-0.1.0rc1.dist-info/METADATA
py_kaos_utils-0.1.0rc1.dist-info/WHEEL
py_kaos_utils-0.1.0rc1.dist-info/top_level.txt
py_kaos_utils-0.1.0rc1.dist-info/RECORD
