Metadata-Version: 2.1
Name: py-kaos-utils
Version: 0.1.0rc1
Summary: Set of utilities and helpers for rapid development of Python applications
Home-page: https://github.com/kaoslabsinc/py-kaos-utils
Author: Kaos Labs Inc.
Author-email: keyvan@keyvanm.com
License: BSD-3-Clause
Keywords: python,rapid developments,utils,utilities,helpers,kaos
Classifier: Environment :: Web Environment
Classifier: Framework :: Django
Classifier: Framework :: Django :: 3.2
Classifier: Intended Audience :: Developers
Classifier: License :: OSI Approved :: BSD License
Classifier: Operating System :: OS Independent
Classifier: Programming Language :: Python
Classifier: Programming Language :: Python :: 3
Classifier: Programming Language :: Python :: 3 :: Only
Classifier: Programming Language :: Python :: 3.7
Classifier: Programming Language :: Python :: 3.8
Classifier: Programming Language :: Python :: 3.9
Classifier: Topic :: Internet :: WWW/HTTP
Classifier: Topic :: Internet :: WWW/HTTP :: Dynamic Content
License-File: LICENSE
Requires-Dist: python-dateutil
Provides-Extra: test
Requires-Dist: tox ; extra == 'test'
Requires-Dist: pytest-pythonpath ; extra == 'test'
Requires-Dist: pytest-cov ; extra == 'test'
